img_lurker.py
img_lurker-1.0.3.dist-info/METADATA
img_lurker-1.0.3.dist-info/WHEEL
img_lurker-1.0.3.dist-info/entry_points.txt
img_lurker-1.0.3.dist-info/licenses/COPYING.wtfpl
img_lurker-1.0.3.dist-info/RECORD
