Metadata-Version: 2.1
Name: img-lurker
Version: 1.0.3
Summary: Web gallery downloader
Project-URL: Homepage, https://gitlab.com/hydrargyrum/img-lurker/
Author-email: Hg <dev@indigo.re>
License-Expression: WTFPL
License-File: COPYING.wtfpl
Keywords: crawling,download,gallery,image,photo,spider
Classifier: Development Status :: 5 - Production/Stable
Classifier: Environment :: Console
Classifier: Intended Audience :: End Users/Desktop
Classifier: License :: Public Domain
Classifier: Operating System :: OS Independent
Classifier: Programming Language :: Python
Classifier: Programming Language :: Python :: 3.6
Classifier: Programming Language :: Python :: 3.7
Classifier: Programming Language :: Python :: 3.8
Classifier: Topic :: Internet
Classifier: Topic :: Internet :: WWW/HTTP :: Browsers
Classifier: Topic :: Internet :: WWW/HTTP :: Indexing/Search
Classifier: Topic :: Multimedia :: Graphics
Classifier: Topic :: System :: Archiving
Classifier: Topic :: Utilities
Requires-Python: >=3.6
Requires-Dist: pillow
Requires-Dist: woob
